preloop/inception/__init__.py
preloop/inception/constructs.py
preloop/inception/models.py
preloop/observability/__init__.py
preloop/observability/model/__init__.py
preloop/observability/model/base.py
preloop/public_api_stubs/__init__.py
preloop/public_api_stubs/api_paths.py
preloop/public_api_stubs/exceptions.py
preloop/public_api_stubs/models.py
preloop/public_api_stubs/preloop_client.py
preloop_sdk-0.2.54.dist-info/LICENSE
preloop_sdk-0.2.54.dist-info/METADATA
preloop_sdk-0.2.54.dist-info/WHEEL
preloop_sdk-0.2.54.dist-info/RECORD
