Metadata-Version: 2.1
Name: preloop-sdk
Version: 0.2.54
Summary: SDK to build and use Preloop functionality in your apps.
Home-page: https://www.preloop.com/
License: Apache-2.0
Keywords: preloop,sdk
Author: Preloop, Inc.
Author-email: engineering@preloop.com
Requires-Python: >=3.11,<4.0
Classifier: License :: OSI Approved :: Apache Software License
Classifier: Programming Language :: Python :: 3
Classifier: Programming Language :: Python :: 3.11
Requires-Dist: pandas (>=2.1.3,<3.0.0)
Requires-Dist: pydantic (>=2.5.2,<3.0.0)
Requires-Dist: requests (>=2.31.0,<3.0.0)
Project-URL: Documentation, https://www.preloop.com/docs
